promptsuite/__init__.py
promptsuite/cli.py
promptsuite/augmentations/__init__.py
promptsuite/augmentations/base.py
promptsuite/augmentations/factory.py
promptsuite/augmentations/other.py
promptsuite/augmentations/utils.py
promptsuite/augmentations/structure/__init__.py
promptsuite/augmentations/structure/enumerate.py
promptsuite/augmentations/structure/fewshot.py
promptsuite/augmentations/structure/shuffle.py
promptsuite/augmentations/text/__init__.py
promptsuite/augmentations/text/context.py
promptsuite/augmentations/text/format_structure.py
promptsuite/augmentations/text/noise.py
promptsuite/augmentations/text/paraphrase.py
promptsuite/core/__init__.py
promptsuite/core/api.py
promptsuite/core/engine.py
promptsuite/core/exceptions.py
promptsuite/core/models.py
promptsuite/core/template_keys.py
promptsuite/core/template_parser.py
promptsuite/generation/__init__.py
promptsuite/generation/few_shot_handler.py
promptsuite/generation/prompt_builder.py
promptsuite/generation/variation_generator.py
promptsuite/shared/__init__.py
promptsuite/shared/constants.py
promptsuite/shared/model_client.py
promptsuite/ui/__init__.py
promptsuite/ui/main.py
promptsuite/ui/pages/generate_variations.py
promptsuite/ui/pages/load.py
promptsuite/ui/pages/results_display.py
promptsuite/ui/pages/template_builder.py
promptsuite/ui/pages/upload_data.py
promptsuite/ui/utils/__init__.py
promptsuite/ui/utils/progress_indicator.py
promptsuite/utils/__init__.py
promptsuite/utils/formatting.py
promptsuite-3.0.7.dist-info/licenses/LICENSE
promptsuite-3.0.7.dist-info/METADATA
promptsuite-3.0.7.dist-info/WHEEL
promptsuite-3.0.7.dist-info/entry_points.txt
promptsuite-3.0.7.dist-info/top_level.txt
promptsuite-3.0.7.dist-info/RECORD
