Metadata-Version: 2.4
Name: promptsuite
Version: 3.0.7
Summary: A tool that creates multi-prompt datasets from single-prompt datasets using templates
Author: Eliya Habba
License: MIT
Project-URL: Homepage, https://github.com/eliyahabba/PromptSuite
Project-URL: Repository, https://github.com/eliyahabba/PromptSuite
Project-URL: Documentation, https://github.com/eliyahabba/PromptSuite/blob/main/README.md
Project-URL: Issues, https://github.com/eliyahabba/PromptSuite/issues
Keywords: ai,prompts,datasets,nlp,machine-learning
Classifier: Development Status :: 4 - Beta
Classifier: Intended Audience :: Developers
Classifier: License :: OSI Approved :: MIT License
Classifier: Operating System :: OS Independent
Classifier: Programming Language :: Python :: 3
Classifier: Programming Language :: Python :: 3.9
Classifier: Programming Language :: Python :: 3.10
Classifier: Programming Language :: Python :: 3.11
Classifier: Programming Language :: Python :: 3.12
Classifier: Topic :: Scientific/Engineering :: Artificial Intelligence
Classifier: Topic :: Software Development :: Libraries :: Python Modules
Requires-Python: >=3.9
License-File: LICENSE
Requires-Dist: pandas>=1.3.0
Requires-Dist: datasets>=2.0.0
Requires-Dist: click>=8.0.0
Requires-Dist: pyyaml>=6.0
Requires-Dist: python-dotenv>=0.19.0
Requires-Dist: together>=0.2.0
Requires-Dist: numpy>=1.21.0
Requires-Dist: streamlit>=1.45.1
Requires-Dist: dotenv>=0.9.9
Requires-Dist: tqdm>=4.67.1
Requires-Dist: openai>=1.91.0
Requires-Dist: matplotlib>=3.5.0
Provides-Extra: ui
Requires-Dist: streamlit>=1.28.0; extra == "ui"
Provides-Extra: dev
Requires-Dist: pytest>=6.0; extra == "dev"
Requires-Dist: black>=22.0; extra == "dev"
Requires-Dist: flake8>=4.0; extra == "dev"
Requires-Dist: streamlit>=1.28.0; extra == "dev"
Dynamic: license-file
